ipywidgets_extended/__init__.py
ipywidgets_extended/dropdown.py
ipywidgets_extended/version.py
ipywidgets_extended/labextension/ipywidgets-extended-1.2.1.tgz
ipywidgets_extended/nbextension/__init__.py
ipywidgets_extended/nbextension/static/extension.js
ipywidgets_extended/nbextension/static/index.js
ipywidgets_extended/nbextension/static/index.js.map
ipywidgets_extended-1.2.1.data/data/etc/jupyter/nbconfig/notebook.d/ipywidgets_extended.json
ipywidgets_extended-1.2.1.data/data/share/jupyter/nbextensions/ipywidgets_extended/extension.js
ipywidgets_extended-1.2.1.dist-info/LICENSE
ipywidgets_extended-1.2.1.dist-info/METADATA
ipywidgets_extended-1.2.1.dist-info/WHEEL
ipywidgets_extended-1.2.1.dist-info/top_level.txt
ipywidgets_extended-1.2.1.dist-info/RECORD
