Metadata-Version: 2.1
Name: ipywidgets-extended
Version: 1.2.1
Summary: Extensions to the Jupyter Widgets in the `ipywidgets` package.
Home-page: https://github.com/CasperWA/ipywidgets-extended
Author: Casper Welzel Andersen
Author-email: casper+github@welzel.nu
License: BSD
Classifier: Development Status :: 3 - Alpha
Classifier: Framework :: Jupyter
Classifier: License :: OSI Approved :: BSD License
Classifier: Operating System :: MacOS :: MacOS X
Classifier: Operating System :: POSIX :: Linux
Classifier: Operating System :: Microsoft :: Windows
Classifier: Programming Language :: Python :: 3 :: Only
Classifier: Programming Language :: Python :: 3.7
Classifier: Programming Language :: Python :: 3.8
Classifier: Programming Language :: Python :: 3.9
Classifier: Topic :: Software Development :: Widget Sets
Requires-Python: >=3.7
License-File: LICENSE
Requires-Dist: ipywidgets (~=7.7)
Requires-Dist: packaging (~=21.3)
Provides-Extra: dev
Requires-Dist: invoke (~=1.7) ; extra == 'dev'
Requires-Dist: pre-commit (~=2.20) ; extra == 'dev'
Requires-Dist: pylint (~=2.14) ; extra == 'dev'
